<?xml version="1.0" encoding="utf-8"?>
<arch:spatialUnit xmlns:arch="http://ochre.lib.uchicago.edu/schema/SpatialUnit/SpatialUnit.xsd" xmlns:oc="http://opencontext.org/schema/space_schema_v1.xsd" xmlns:dc="http://purl.org/dc/elements/1.1/" xmlns:gml="http://www.opengis.net/gml" UUID="B7C12806-BB4D-4FEF-FBD8-DBF3811F100F" ownedBy="8492AEC3-E406-44C6-03CA-2BF280D8F5B0">
  <arch:name>
    <arch:string>13VB100</arch:string>
  </arch:name>
  <oc:item_class>
    <oc:name>Site</oc:name>
    <oc:iconURI>http://opencontext.org/database/ui_images/med_oc_icons/site_50x50.jpg</oc:iconURI>
  </oc:item_class>
  <arch:observations>
    <arch:observation obsNumber="1">
      <oc:obs_metadata>
        <oc:source>z_6_a49220780</oc:source>
      </oc:obs_metadata>
      <arch:properties>
        <arch:property>
          <arch:variableID>3FC97853-08FA-415F-ED27-FB6DFC513B89</arch:variableID>
          <arch:integer>100</arch:integer>
          <oc:propid href="http://opencontext.org/properties/DED50343-8B75-42D1-839A-60F98932120E">DED50343-8B75-42D1-839A-60F98932120E</oc:propid>
          <oc:var_label type="integer">Site number</oc:var_label>
          <oc:show_val>100</oc:show_val>
        </arch:property>
        <arch:property>
          <arch:variableID>FAC1EE4D-E89F-4CF2-8337-CF1E344665AD</arch:variableID>
          <arch:valueID>D2A0D112-1E10-48E7-792B-40BA720AFE69</arch:valueID>
          <oc:propid href="http://opencontext.org/properties/857DBD0C-3668-42BC-45FF-00BDE6CD89A3">857DBD0C-3668-42BC-45FF-00BDE6CD89A3</oc:propid>
          <oc:var_label type="nominal">Auxiliary ID</oc:var_label>
          <oc:show_val>none</oc:show_val>
        </arch:property>
        <arch:property>
          <arch:variableID>852FD445-E7F9-48C4-1C0F-6539399AB57A</arch:variableID>
          <arch:valueID>75097454-D3D5-4FAE-97A3-834F8224D854</arch:valueID>
          <oc:propid href="http://opencontext.org/properties/3281B58D-F02F-49D1-121C-4EE083E70FEC">3281B58D-F02F-49D1-121C-4EE083E70FEC</oc:propid>
          <oc:var_label type="nominal">Cultural affiliation</oc:var_label>
          <oc:show_val>Prehistoric</oc:show_val>
          <oc:linkedData>
            <oc:relationLink localType="variable" localID="852FD445-E7F9-48C4-1C0F-6539399AB57A" href="http://opencontext.org/vocabularies/dinaa/00001">
              <oc:vocabulary href="http://opencontext.org/vocabularies/dinaa">DINAA Vocabulary</oc:vocabulary>
              <oc:label>Has period</oc:label>
              <oc:targetLink localType="property" localID="3281B58D-F02F-49D1-121C-4EE083E70FEC" localURI="http://opencontext.org/properties/3281B58D-F02F-49D1-121C-4EE083E70FEC" href="http://opencontext.org/vocabularies/dinaa/00028">
                <oc:vocabulary href="http://opencontext.org/vocabularies/dinaa">DINAA Vocabulary</oc:vocabulary>
                <oc:label>Prehistoric Undifferentiated</oc:label>
              </oc:targetLink>
            </oc:relationLink>
          </oc:linkedData>
        </arch:property>
        <arch:property>
          <arch:variableID>D6FAF80F-3ABA-4686-0085-B81B0700510A</arch:variableID>
          <arch:valueID>AAF60E0B-4ABA-4D0F-42B5-74AF0B703965</arch:valueID>
          <oc:propid href="http://opencontext.org/properties/03587B7B-69A6-4F17-3907-F74241728A16">03587B7B-69A6-4F17-3907-F74241728A16</oc:propid>
          <oc:var_label type="alphanumeric">Basis of phasing</oc:var_label>
          <oc:show_val>other diagnostic artifacts</oc:show_val>
        </arch:property>
        <arch:property>
          <arch:variableID>FC358103-88E5-4966-E3E9-C7F55564DAE0</arch:variableID>
          <arch:valueID>5CEE593F-23EB-4DC0-4415-4E50BDD99311</arch:valueID>
          <oc:propid href="http://opencontext.org/properties/445644C1-3CDA-421D-7F1C-012CBC5900D5">445644C1-3CDA-421D-7F1C-012CBC5900D5</oc:propid>
          <oc:var_label type="alphanumeric">Describe</oc:var_label>
          <oc:show_val>Diagnostic prehistoric period artifacts</oc:show_val>
        </arch:property>
        <arch:property>
          <arch:variableID>FC839713-7D01-46DA-2DA9-DCB7D16F06A5</arch:variableID>
          <arch:valueID>55B18B28-EB90-4E86-2A00-147481863B37</arch:valueID>
          <oc:propid href="http://opencontext.org/properties/BF18F592-9EBA-4033-EE34-C2F95CAF5D4A">BF18F592-9EBA-4033-EE34-C2F95CAF5D4A</oc:propid>
          <oc:var_label type="nominal">Artifact type</oc:var_label>
          <oc:show_val>Stone, chipped, debitage</oc:show_val>
        </arch:property>
        <arch:property>
          <arch:variableID>FC839713-7D01-46DA-2DA9-DCB7D16F06A5</arch:variableID>
          <arch:valueID>A79433F2-B89F-47AA-26C5-3EC8F16B40AD</arch:valueID>
          <oc:propid href="http://opencontext.org/properties/F6057A7D-3C37-40E8-BE7C-725D71BC1461">F6057A7D-3C37-40E8-BE7C-725D71BC1461</oc:propid>
          <oc:var_label type="nominal">Artifact type</oc:var_label>
          <oc:show_val>Stone, ground or pecked</oc:show_val>
        </arch:property>
        <arch:property>
          <arch:variableID>8B0E5EBC-5BF9-4294-1A26-A923AF71C625</arch:variableID>
          <arch:valueID>017C4122-53AC-4D40-2242-9DB5E0B7F81D</arch:valueID>
          <oc:propid href="http://opencontext.org/properties/FF83AB91-515A-4F0F-EE2B-13CD035A2DD0">FF83AB91-515A-4F0F-EE2B-13CD035A2DD0</oc:propid>
          <oc:var_label type="alphanumeric">Artifact description</oc:var_label>
          <oc:show_val>celt</oc:show_val>
        </arch:property>
        <arch:property>
          <arch:variableID>8B0E5EBC-5BF9-4294-1A26-A923AF71C625</arch:variableID>
          <arch:valueID>45A820DD-BABD-4D10-2A9B-B8D9C829FCBF</arch:valueID>
          <oc:propid href="http://opencontext.org/properties/4B51DBCE-E4BC-4936-9EEC-1DEA3C06D860">4B51DBCE-E4BC-4936-9EEC-1DEA3C06D860</oc:propid>
          <oc:var_label type="alphanumeric">Artifact description</oc:var_label>
          <oc:show_val>waste flakes</oc:show_val>
        </arch:property>
        <arch:property>
          <arch:variableID>8B0E5EBC-5BF9-4294-1A26-A923AF71C625</arch:variableID>
          <arch:valueID>7BB9B7C4-DF23-47F3-52CC-CDB690346530</arch:valueID>
          <oc:propid href="http://opencontext.org/properties/7F9CB474-3C95-4B9F-12DA-D791EDE30BE1">7F9CB474-3C95-4B9F-12DA-D791EDE30BE1</oc:propid>
          <oc:var_label type="alphanumeric">Artifact description</oc:var_label>
          <oc:show_val>stone axe</oc:show_val>
        </arch:property>
        <arch:property>
          <arch:variableID>A992ED90-25E0-4CD3-5F31-88FCB6040D02</arch:variableID>
          <arch:valueID>BA33EE96-4FB1-4DB5-8421-2E0AC9E9A82E</arch:valueID>
          <oc:propid href="http://opencontext.org/properties/14C2A4DA-F342-41AB-C830-F220DABBB440">14C2A4DA-F342-41AB-C830-F220DABBB440</oc:propid>
          <oc:var_label type="nominal">Basis of modification</oc:var_label>
          <oc:show_val>Unknown</oc:show_val>
        </arch:property>
        <arch:property>
          <arch:variableID>00EAF93A-7E2D-4AB4-2197-0E461336B103</arch:variableID>
          <arch:valueID>6900400F-E1E5-4645-4BA9-48F810D281D7</arch:valueID>
          <oc:propid href="http://opencontext.org/properties/6AFE0578-1E8B-47B7-9474-7598FAFFF5F1">6AFE0578-1E8B-47B7-9474-7598FAFFF5F1</oc:propid>
          <oc:var_label type="nominal">Threat type</oc:var_label>
          <oc:show_val>Erosion/weathering/rodents</oc:show_val>
        </arch:property>
        <arch:property>
          <arch:variableID>56A2AFFB-5EA5-4895-9DB2-CD05D2D5CA58</arch:variableID>
          <arch:valueID>D34AE432-FB44-4976-9143-EC4C8577ADD9</arch:valueID>
          <oc:propid href="http://opencontext.org/properties/913260CD-E5FD-421F-239A-69A1FEB974F6">913260CD-E5FD-421F-239A-69A1FEB974F6</oc:propid>
          <oc:var_label type="nominal">Recommendations</oc:var_label>
          <oc:show_val>Field check</oc:show_val>
        </arch:property>
        <arch:property>
          <arch:variableID>B03486F4-CF77-4BE8-40D2-6D7B53C8EB74</arch:variableID>
          <arch:valueID>58391FBF-402D-4867-9640-759C33232687</arch:valueID>
          <oc:propid href="http://opencontext.org/properties/D02DCC0E-3B8F-4CB1-E0B3-76B8BA8B050D">D02DCC0E-3B8F-4CB1-E0B3-76B8BA8B050D</oc:propid>
          <oc:var_label type="nominal">Land use</oc:var_label>
          <oc:show_val>Pasture/grass</oc:show_val>
        </arch:property>
        <arch:property>
          <arch:variableID>2C26AA89-435D-4529-373F-A0E4AC09F32F</arch:variableID>
          <arch:valueID>883E8D8E-2289-4E89-1AF9-F253955B083B</arch:valueID>
          <oc:propid href="http://opencontext.org/properties/13B718FC-4371-4F34-FB5C-C01C176ACD10">13B718FC-4371-4F34-FB5C-C01C176ACD10</oc:propid>
          <oc:var_label type="nominal">Site function</oc:var_label>
          <oc:show_val>Prehistoric scatter</oc:show_val>
        </arch:property>
      </arch:properties>
    </arch:observation>
  </arch:observations>
  <oc:context>
    <oc:tree id="default">
      <oc:parent href="http://opencontext.org/subjects/2A1B75E6-8C79-49B9-873A-A2E006669691">
        <oc:name>United States</oc:name>
        <oc:id>2A1B75E6-8C79-49B9-873A-A2E006669691</oc:id>
        <oc:level>3</oc:level>
        <oc:item_class>
          <oc:name>Region</oc:name>
          <oc:iconURI>http://opencontext.org/database/ui_images/med_oc_icons/region_30x30.jpg</oc:iconURI>
        </oc:item_class>
      </oc:parent>
      <oc:parent href="http://opencontext.org/subjects/21268C42-F4B1-4D37-C130-AA69FFD3E7F9">
        <oc:name>Iowa</oc:name>
        <oc:id>21268C42-F4B1-4D37-C130-AA69FFD3E7F9</oc:id>
        <oc:level>2</oc:level>
        <oc:item_class>
          <oc:name>Region</oc:name>
          <oc:iconURI>http://opencontext.org/database/ui_images/med_oc_icons/region_30x30.jpg</oc:iconURI>
        </oc:item_class>
      </oc:parent>
      <oc:parent href="http://opencontext.org/subjects/D723A052-2DC8-456C-2383-82E566C0218F">
        <oc:name>Van Buren</oc:name>
        <oc:id>D723A052-2DC8-456C-2383-82E566C0218F</oc:id>
        <oc:level>1</oc:level>
        <oc:item_class>
          <oc:name>Region</oc:name>
          <oc:iconURI>http://opencontext.org/database/ui_images/med_oc_icons/region_30x30.jpg</oc:iconURI>
        </oc:item_class>
      </oc:parent>
    </oc:tree>
  </oc:context>
  <oc:metadata>
    <dc:title>Iowa Site Files: 13VB100 (Site)</dc:title>
    <dc:publisher>Open Context</dc:publisher>
    <dc:date>2014-03-16</dc:date>
    <dc:subject>archaeology</dc:subject>
    <dc:subject>cultural resource management</dc:subject>
    <dc:subject>DINAA</dc:subject>
    <dc:subject>Iowa</dc:subject>
    <dc:subject>North America</dc:subject>
    <dc:subject>site files</dc:subject>
    <dc:subject>state historical preservation office</dc:subject>
    <dc:creator href="http://opencontext.org/persons/">Iowa Office of the State Archaeologist (OSA)</dc:creator>
    <dc:identifier>http://opencontext.org/subjects/B7C12806-BB4D-4FEF-FBD8-DBF3811F100F</dc:identifier>
    <oc:project_name href="http://opencontext.org/projects/8492AEC3-E406-44C6-03CA-2BF280D8F5B0">Iowa Site Files</oc:project_name>
    <oc:pub_date>2014-03-16T00:00:00-07:00</oc:pub_date>
    <oc:coins>ctx_ver=Z39.88-2004&amp;rft_val_fmt=info%3Aofi%2Ffmt%3Akev%3Amtx%3Adc&amp;rft_val_fmt=info%3Aofi%2Ffmt%3Akev%3Amtx%3Adc&amp;rft.type=dataset&amp;rft.title=Iowa+Site+Files%3A+13VB100+%28Site%29&amp;rft.publisher=Open+Context&amp;rft.source=Open+Context&amp;rft.subject=archaeology&amp;rft.subject=cultural+resource+management&amp;rft.subject=DINAA&amp;rft.subject=Iowa&amp;rft.subject=North+America&amp;rft.subject=site+files&amp;rft.subject=state+historical+preservation+office&amp;rft.creator=Iowa+Office+of+the+State+Archaeologist+%28OSA%29&amp;rft.identifier=http%3A%2F%2Fopencontext.org%2Fsubjects%2FB7C12806-BB4D-4FEF-FBD8-DBF3811F100F</oc:coins>
    <oc:geo_reference>
      <oc:geo_lat>40.913479212846</oc:geo_lat>
      <oc:geo_long>-92.197265625</oc:geo_long>
      <oc:metasource ref_type="self" href="http://opencontext.org/subjects/B7C12806-BB4D-4FEF-FBD8-DBF3811F100F" specificity="-11">
        <oc:note>Approximated by geotile to zoom level 11</oc:note>
        <oc:source_name>13VB100</oc:source_name>
        <oc:source_id>B7C12806-BB4D-4FEF-FBD8-DBF3811F100F</oc:source_id>
      </oc:metasource>
    </oc:geo_reference>
    <oc:copyright_lic href="http://creativecommons.org/publicdomain/zero/1.0/">
      <oc:lic_name>Zero (Public Domain)</oc:lic_name>
      <oc:lic_vers>1</oc:lic_vers>
      <oc:lic_URI>http://creativecommons.org/publicdomain/zero/1.0/</oc:lic_URI>
      <oc:lic_icon_URI>http://i.creativecommons.org/p/zero/1.0/88x31.png</oc:lic_icon_URI>
    </oc:copyright_lic>
  </oc:metadata>
  <oc:social_usage>
    <oc:last_updated>2014-03-17T10:25:14-07:00</oc:last_updated>
    <oc:item_views>
      <oc:count>1</oc:count>
      <oc:view_time>2014/03/17 10:25:14</oc:view_time>
    </oc:item_views>
    <oc:user_tags>
      <oc:tag type="chronological" status="public">
        <oc:name>(9,550 BCE - 1673 CE)</oc:name>
        <oc:chrono isDuration="true">
          <oc:time_start>-9550</oc:time_start>
          <oc:time_finish>1673</oc:time_finish>
          <oc:metasource ref_type="self" href="http://opencontext.org/subjects/B7C12806-BB4D-4FEF-FBD8-DBF3811F100F">
            <oc:source_name>13VB100</oc:source_name>
            <oc:source_id>B7C12806-BB4D-4FEF-FBD8-DBF3811F100F</oc:source_id>
          </oc:metasource>
        </oc:chrono>
        <oc:tag_creator id="oc">
          <oc:creator_name>Open Context Editors</oc:creator_name>
          <oc:set_label>Default set</oc:set_label>
          <oc:set_id>Default set</oc:set_id>
          <oc:set_date>2014-03-16T13:16:31-07:00</oc:set_date>
        </oc:tag_creator>
      </oc:tag>
    </oc:user_tags>
  </oc:social_usage>
</arch:spatialUnit>
